td_ml_datamodel_create/__init__.py
td_ml_datamodel_create/create_datamodel.py
td_ml_datamodel_create-0.1.9.dist-info/METADATA
td_ml_datamodel_create-0.1.9.dist-info/WHEEL
td_ml_datamodel_create-0.1.9.dist-info/licenses/LICENSE
td_ml_datamodel_create-0.1.9.dist-info/RECORD
