Metadata-Version: 2.3
Name: td_ml_datamodel_create
Version: 0.1.9
Summary: Auto Build TI ElasticCube datamodel via API
Project-URL: Homepage, https://github.com/treasure-data-ps/td_ml_libraries/tree/main/td_ml_datamodel_create
Project-URL: Bug Tracker, https://github.com/treasure-data-ps/td_ml_libraries/tree/main/td_ml_datamodel_create
Author-email: Dilyan Kovachev <pruchka@gmail.com>
License: Copyright © 2022 Treasure Data, Inc. (or its affiliates). All rights reserved
License-File: LICENSE
Classifier: Operating System :: OS Independent
Classifier: Programming Language :: Python :: 3
Requires-Python: >=3.8
